statisticalrl_learners/__init__.py
statisticalrl_learners/Generic/Qlearning.py
statisticalrl_learners/Generic/Random.py
statisticalrl_learners/Generic/__init__.py
statisticalrl_learners/MABs/BESA.py
statisticalrl_learners/MABs/FTL.py
statisticalrl_learners/MABs/IMED.py
statisticalrl_learners/MABs/Oracle.py
statisticalrl_learners/MABs/TS.py
statisticalrl_learners/MABs/UCB.py
statisticalrl_learners/MABs/Uniform.py
statisticalrl_learners/MABs/__init__.py
statisticalrl_learners/MABs/utils.py
statisticalrl_learners/MDPs_discrete/AgentInterface.py
statisticalrl_learners/MDPs_discrete/Human.py
statisticalrl_learners/MDPs_discrete/IMED_RL.py
statisticalrl_learners/MDPs_discrete/KLUCRL.py
statisticalrl_learners/MDPs_discrete/MED_RL.py
statisticalrl_learners/MDPs_discrete/PSRL.py
statisticalrl_learners/MDPs_discrete/UCRL2.py
statisticalrl_learners/MDPs_discrete/UCRL2B.py
statisticalrl_learners/MDPs_discrete/UCRL3.py
statisticalrl_learners/MDPs_discrete/__init__.py
statisticalrl_learners/MDPs_discrete/utils.py
statisticalrl_learners/MDPs_discrete/Equivalence/CUCRL.py
statisticalrl_learners/MDPs_discrete/Equivalence/UCRL_equivalence.py
statisticalrl_learners/MDPs_discrete/Equivalence/__init__.py
statisticalrl_learners/MDPs_discrete/Equivalence/equivalence.py
statisticalrl_learners/MDPs_discrete/KnownDynamics/IMEDKTP.py
statisticalrl_learners/MDPs_discrete/KnownDynamics/PSRL_KD.py
statisticalrl_learners/MDPs_discrete/KnownDynamics/TS_KD.py
statisticalrl_learners/MDPs_discrete/KnownDynamics/UCB_KD.py
statisticalrl_learners/MDPs_discrete/KnownDynamics/UCRL3_KD.py
statisticalrl_learners/MDPs_discrete/KnownDynamics/__init__.py
statisticalrl_learners/MDPs_discrete/Optimal/BlackwellOptimalControl.py
statisticalrl_learners/MDPs_discrete/Optimal/OptimalControl.py
statisticalrl_learners/MDPs_discrete/Optimal/__init__.py
statisticalrl_learners-2.2507.dist-info/licenses/LICENSE
statisticalrl_learners-2.2507.dist-info/METADATA
statisticalrl_learners-2.2507.dist-info/WHEEL
statisticalrl_learners-2.2507.dist-info/top_level.txt
statisticalrl_learners-2.2507.dist-info/RECORD
