Metadata-Version: 2.4
Name: statisticalRL-learners
Version: 2.2507
Summary: Learners for the Statistical Reinforcement Learning project
Author-email: Odalric-Ambym Maillard <odalric.maillard@inria.fr>
License: MIT
Project-URL: Homepage, https://github.com/StatisticalRL/learners
Requires-Python: >=3.8
License-File: LICENSE
Requires-Dist: six==1.16.0
Requires-Dist: gymnasium==1.2.0
Requires-Dist: numpy==1.24.3
Requires-Dist: networkx==2.8.8
Requires-Dist: matplotlib==3.7.2
Requires-Dist: scipy==1.15.2
Requires-Dist: pydot==1.4.2
Dynamic: license-file
